.gitignore
README.rst
setup.py
docs/Makefile
docs/make.bat
docs/source/conf.py
docs/source/index.rst
docs/source/modules.rst
docs/source/ndb_adapter.rst
ndb_adapter/__init__.py
ndb_adapter/advanced_search_options.py
ndb_adapter/dna_search_options.py
ndb_adapter/enums.py
ndb_adapter/html_parser.py
ndb_adapter/ndb.py
ndb_adapter/ndb_base.py
ndb_adapter/ndb_download.py
ndb_adapter/report_parser.py
ndb_adapter/rna_search_options.py
ndb_adapter/search_options.py
ndb_adapter/search_report.py
ndb_adapter/search_result.py
ndb_adapter/statistics.py
ndb_adapter/summary_result.py
ndb_adapter.egg-info/PKG-INFO
ndb_adapter.egg-info/SOURCES.txt
ndb_adapter.egg-info/dependency_links.txt
ndb_adapter.egg-info/requires.txt
ndb_adapter.egg-info/top_level.txt
tests/test.xls
tests/test_download.py
tests/test_html_parser.py
tests/test_ndb.py
tests/test_report_parser.py
tests/test_search_options.py