Metadata-Version: 1.1
Name: ndb-adapter
Version: 1.3
Summary: Adapter for http://ndbserver.rutgers.edu/ created for biologists, bioinformatics etc.
Home-page: https://github.com/Michsior14/ndb_adapter
Author: Michal Mrozek
Author-email: michau.mrozek@student.uj.edu.pl
License: MIT
Keywords: ndbserver,ndb,nucleic acid database,adapter
Platform: UNKNOWN
Classifier: Development Status :: 5 - Production/Stable
Classifier: Environment :: Console
Classifier: Intended Audience :: End Users/Desktop
Classifier: Intended Audience :: Developers
Classifier: License :: OSI Approved :: MIT License
Classifier: Programming Language :: Python :: 3 :: Only
Classifier: Programming Language :: Python :: 3.0
Classifier: Programming Language :: Python :: 3.1
Classifier: Programming Language :: Python :: 3.2
Classifier: Programming Language :: Python :: 3.3
Classifier: Programming Language :: Python :: 3.4
Classifier: Programming Language :: Python :: 3.5
Classifier: Operating System :: OS Independent
Classifier: Topic :: Database
Classifier: Topic :: Internet
Classifier: Topic :: Scientific/Engineering :: Bio-Informatics
Classifier: Topic :: Scientific/Engineering :: Chemistry
Classifier: Topic :: Software Development :: Libraries :: Python Modules
